README.rst
dockman.py
setup.py
dockman.egg-info/PKG-INFO
dockman.egg-info/SOURCES.txt
dockman.egg-info/dependency_links.txt
dockman.egg-info/not-zip-safe
dockman.egg-info/requires.txt
dockman.egg-info/top_level.txt