Metadata-Version: 1.0
Name: dockman
Version: 0.4
Summary: A webservice that runs docker builds/deployments on docker webhooks
Home-page: http://github.com/TronPaul/dockman
Author: Mark McGuire
Author-email: mark.b.mcg@gmail.com
License: UNKNOWN
Platform: UNKNOWN
